computegraph/__init__.py
computegraph/draw/__init__.py
computegraph/draw/add_edge.py
computegraph/draw/draw.py
computegraph/draw/ngraph.py
computegraph/draw/README.md
computegraph/dynamic.py
computegraph/graph.py
computegraph/jaxify.py
computegraph/options.py
computegraph/types.py
computegraph/utils.py
computegraph-0.4.5.dist-info/LICENSE
computegraph-0.4.5.dist-info/METADATA
computegraph-0.4.5.dist-info/WHEEL
computegraph-0.4.5.dist-info/RECORD
